via_lighting_api.py
tools/__init__.py
tools/keyboard_info_viewer.py
via_lighting_api_osfix-0.2.1.dist-info/licenses/LICENSE
via_lighting_api_osfix-0.2.1.dist-info/METADATA
via_lighting_api_osfix-0.2.1.dist-info/WHEEL
via_lighting_api_osfix-0.2.1.dist-info/entry_points.txt
via_lighting_api_osfix-0.2.1.dist-info/top_level.txt
via_lighting_api_osfix-0.2.1.dist-info/RECORD
