Metadata-Version: 2.4
Name: via-lighting-api-osfix
Version: 0.2.1
Summary: OS fix to the original package. This Python API provides an interface for controlling the RGB lighting of keyboards that support the VIA protocol. It allows you to dynamically change the brightness, effect, effect speed, and color of the lighting.
Home-page: https://github.com/andrulonis/via-lighting-api
Author: andrulonis
License: MIT
Keywords: via api
License-File: LICENSE
Requires-Dist: hidapi
Dynamic: author
Dynamic: description
Dynamic: description-content-type
Dynamic: home-page
Dynamic: keywords
Dynamic: license
Dynamic: license-file
Dynamic: requires-dist
Dynamic: summary
